SetSolver1/MODE.py
SetSolver1/MathSet.py
SetSolver1/MultiMathSet.py
SetSolver1/RelationMathSet.py
SetSolver1/ResultWay.py
SetSolver1/SimpleMathSet.py
SetSolver1/TinyMathSet.py
SetSolver1/__init__.py
SetSolver1/main.py
SetSolver1-1!2021.12.2.dist-info/LICENSE
SetSolver1-1!2021.12.2.dist-info/METADATA
SetSolver1-1!2021.12.2.dist-info/WHEEL
SetSolver1-1!2021.12.2.dist-info/top_level.txt
SetSolver1-1!2021.12.2.dist-info/RECORD
