Metadata-Version: 2.1
Name: SetSolver1
Version: 1!2021.12.2
Summary: This script is solving set problems by brute-force.
Home-page: https://github.com/LukasWestholt/SetSolver1
Author: lukaswestholt
Author-email: support@lukaswestholt.de
License: GPLv3
Project-URL: Bug Tracker, https://github.com/LukasWestholt/SetSolver1/issues
Platform: UNKNOWN
Classifier: Programming Language :: Python :: 3
Classifier: License :: OSI Approved :: GNU General Public License v3 (GPLv3)
Classifier: Operating System :: OS Independent
Classifier: Topic :: Scientific/Engineering :: Mathematics
Requires-Python: >=3.10
License-File: LICENSE
